pretix_wallet/__init__.py
pretix_wallet/api.py
pretix_wallet/apps.py
pretix_wallet/elements.py
pretix_wallet/exporters.py
pretix_wallet/forms.py
pretix_wallet/middleware.py
pretix_wallet/models.py
pretix_wallet/payment.py
pretix_wallet/signals.py
pretix_wallet/urls.py
pretix_wallet/views.py
pretix_wallet/asn1/pretixWallet.asn
pretix_wallet/locale/de/LC_MESSAGES/django.mo
pretix_wallet/locale/de/LC_MESSAGES/django.po
pretix_wallet/locale/de_Informal/.gitkeep
pretix_wallet/locale/de_Informal/LC_MESSAGES/django.mo
pretix_wallet/locale/de_Informal/LC_MESSAGES/django.po
pretix_wallet/migrations/0001_initial.py
pretix_wallet/migrations/0002_alter_wallet_pan_and_more.py
pretix_wallet/migrations/0003_wallet_settingsstore.py
pretix_wallet/migrations/0004_plugin_level.py
pretix_wallet/migrations/0005_wallet_order_and_more.py
pretix_wallet/migrations/__init__.py
pretix_wallet/static/pretix_wallet/.gitkeep
pretix_wallet/templates/pretix_wallet/.gitkeep
pretix_wallet/templates/pretix_wallet/order/balance.html
pretix_wallet/templates/pretix_wallet/organizers/event_settings.html
pretix_wallet/templates/pretix_wallet/organizers/settings.html
pretix_wallet/templates/pretix_wallet/organizers/wallet.html
pretix_wallet/templates/pretix_wallet/organizers/wallet_settings.html
pretix_wallet/templates/pretix_wallet/organizers/wallets.html
pretix_wallet/templates/pretix_wallet/payment/checkout_confirm.html
pretix_wallet/templates/pretix_wallet/payment/method_form.html
pretix_wallet/templates/pretix_wallet/payment/payment_control.html
pretix_wallet-1.6.3.dist-info/licenses/LICENSE.md
pretix_wallet-1.6.3.dist-info/METADATA
pretix_wallet-1.6.3.dist-info/WHEEL
pretix_wallet-1.6.3.dist-info/entry_points.txt
pretix_wallet-1.6.3.dist-info/top_level.txt
pretix_wallet-1.6.3.dist-info/RECORD
