Metadata-Version: 2.4
Name: pretix-wallet
Version: 1.6.3
Summary: Wallet payment system for Pretix
Author-email: Q Misell <q@magicalcodewit.ch>
Maintainer-email: Q Misell <q@magicalcodewit.ch>
License-Expression: EUPL-1.2
Project-URL: homepage, https://github.com/TheEnbyperor/pretix-wallet
Project-URL: repository, https://github.com/TheEnbyperor/pretix-wallet
Keywords: pretix
License-File: LICENSE.md
Requires-Dist: pretix-uic-barcode>=1.3.0
Requires-Dist: asn1tools
Dynamic: license-file
